geranslator/__init__.py
geranslator/geranslator.py
geranslator/command_line/__init__.py
geranslator/command_line/command_line.py
geranslator/config/__init__.py
geranslator/config/config.py
geranslator/config/samples/__init__.py
geranslator/config/samples/laravel.py
geranslator/config/samples/sample.py
geranslator/config/samples/symfony.py
geranslator/exceptions/ConfigKeyNotFound.py
geranslator/exceptions/ExtensionNotSupported.py
geranslator/exceptions/FileNotFound.py
geranslator/exceptions/MissingExtension.py
geranslator/exceptions/MissingOriginLang.py
geranslator/exceptions/MissingProvider.py
geranslator/exceptions/MissingTargetLang.py
geranslator/exceptions/OriginLangFileNotFound.py
geranslator/exceptions/ProviderNotFound.py
geranslator/exceptions/__init__.py
geranslator/files_manager/__init__.py
geranslator/files_manager/files_manager.py
geranslator/files_manager/extensions/__init__.py
geranslator/files_manager/extensions/abstractExtension.py
geranslator/files_manager/extensions/json.py
geranslator/files_manager/extensions/po.py
geranslator/files_manager/extensions/yaml.py
geranslator/guess/__init__.py
geranslator/guess/guess.py
geranslator/languages/__init__.py
geranslator/languages/dictionary.yml
geranslator/languages/languages.py
geranslator/provider/__init__.py
geranslator/provider/provider.py
geranslator/provider/providers/__init__.py
geranslator/provider/providers/abstractProvider.py
geranslator/provider/providers/deepl.py
geranslator/provider/providers/google.py
geranslator-2.0.2.dist-info/licenses/LICENSE
geranslator-2.0.2.dist-info/METADATA
geranslator-2.0.2.dist-info/WHEEL
geranslator-2.0.2.dist-info/entry_points.txt
geranslator-2.0.2.dist-info/top_level.txt
geranslator-2.0.2.dist-info/RECORD
