Metadata-Version: 2.4
Name: geranslator
Version: 2.0.2
Summary: Translate your translation files
Home-page: https://github.com/faissaloux/geranslator
Author: Faissal Wahabali
Author-email: fwahabali@gmail.com
License: MIT
Project-URL: Source, https://github.com/faissaloux/geranslator
Project-URL: Documentation, https://geranslator.faissaloux.com
Project-URL: Author, https://www.faissaloux.com
Keywords: translation,translation files,translate
Classifier: Development Status :: 5 - Production/Stable
Classifier: Operating System :: OS Independent
Classifier: Programming Language :: Python :: 3.10
Classifier: Programming Language :: Python :: 3.11
Classifier: Programming Language :: Python :: 3.12
Classifier: Programming Language :: Python :: 3.13
Classifier: Programming Language :: Python :: 3.14
Classifier: Typing :: Typed
Requires-Python: <3.15,>=3.10
License-File: LICENSE
Requires-Dist: PyYAML>=6.0.3
Requires-Dist: cffi>=2.0.0
Requires-Dist: packaging>=25.0
Requires-Dist: polib>=1.2.0
Requires-Dist: selenium>=4.40.0
Requires-Dist: termspark>=3.0.0
Requires-Dist: typer>=0.21.0
Requires-Dist: types-PyYAML>=6.0
Requires-Dist: types-polib>=1.2.0
Requires-Dist: webdriver-manager>=4.0.2
Provides-Extra: dev
Requires-Dist: black>=26.1.0; extra == "dev"
Requires-Dist: isort>=7.0.0; extra == "dev"
Requires-Dist: mypy>=1.19.0; extra == "dev"
Requires-Dist: pre-commit>=4.5.0; extra == "dev"
Requires-Dist: pytest>=9.0.0; extra == "dev"
Requires-Dist: pytest-cov>=7.0.0; extra == "dev"
Requires-Dist: pytest-mock>=3.15.0; extra == "dev"
Provides-Extra: docs
Requires-Dist: mkdocs>=1.6.0; extra == "docs"
Requires-Dist: mkdocs-material>=9.7.1; extra == "docs"
Requires-Dist: pymdown-extensions>=10.20; extra == "docs"
Dynamic: license-file
